upnpinfo/__init__.py
upnpinfo/cli.py
upnpinfo/display.py
upnpinfo/upnp.py
upnpinfo-1.1.0.dist-info/LICENSE
upnpinfo-1.1.0.dist-info/METADATA
upnpinfo-1.1.0.dist-info/WHEEL
upnpinfo-1.1.0.dist-info/entry_points.txt
upnpinfo-1.1.0.dist-info/top_level.txt
upnpinfo-1.1.0.dist-info/RECORD
