Metadata-Version: 2.1
Name: upnpinfo
Version: 1.1.0
Summary: Retrieve UPnP device information from the local network
Author: Mike Joblin
License: MIT License
Project-URL: Homepage, https://github.com/mjoblin/upnpinfo
Classifier: Programming Language :: Python :: 3
Classifier: License :: OSI Approved :: MIT License
Classifier: Operating System :: OS Independent
Requires-Python: >=3.8
License-File: LICENSE
Requires-Dist: rich >=13.4.2
Requires-Dist: upnpclient <2,>=1.0.3
Requires-Dist: click >=8.1.7
Provides-Extra: dev
Requires-Dist: black[d] ; extra == 'dev'
